{
  "experiments": [
    {
      "id": "glassmorphism-card",
      "title": "Glassmorphism Card",
      "description": "Frosted glass effect with backdrop blur",
      "imageUrl": "https://images.unsplash.com/photo-1460925895917-afdab827c52f?w=400&h=300&fit=crop",
      "gradient": "from-blue-500 to-cyan-500",
      "tags": ["Design", "UI"],
      "tag": "Design",
      "url": "/labs/experiments/glassmorphism-card",
      "featured": true
    }
  ],
  "details": {
    "glassmorphism-card": {
      "title": "Glassmorphism Card",
      "subtitle": "Frosted Glass UI Pattern",
      "description": "Frosted glass effect with backdrop blur, subtle borders, and elegant hover states. A modern UI pattern that creates depth and visual interest.",
      "tag": "Design",
      "gradient": "from-blue-500 to-cyan-500",
      "tags": ["Design", "UI", "CSS", "Tailwind"],
      "techStack": ["CSS", "Tailwind CSS", "Framer Motion"],
      "codeSnippet": "<GlassCard\n  blurIntensity=\"lg\"\n  title=\"Clickable Card\"\n  description=\" This card has an onClick handler and is keyboard accessible. Try clicking or using Tab + Enter!\"\n  aria-label=\"Clickable Card\"\n  index={0}\n  onClick={() => alert(\"Card clicked! 🎉\")}\n/>",
      "features": [
        "Backdrop blur effect",
        "Semi-transparent backgrounds",
        "Layered depth with shadows",
        "Smooth hover transitions",
        "Works on any background"
      ],
      "liveUrl": "",
      "githubUrl": "https://github.com/haelostudios/labs/tree/main/experiments/glassmorphism-card"
    }
  }
}
